{"coin":{"id":"2539","title":"Переславль-Залесский","seriesName":"Золотое кольцо России","imageUrl":"/image/coins/5617-0005.webp","imageUrls":["/image/coins/5617-0005.webp","/image/coins/5617-0005r.webp"],"inCollection":false,"mintName":"Московский монетный двор","mintShort":"ММД","mintCountry":"Россия","year":2008,"faceValue":"100 рублей","metal":"Серебро/золото","metalCode":"Au","metalColor":"#FFD700","metalCodes":["Au","Ag"],"mintage":250,"weightG":"124,40 / 84,60","weightOz":"1/2 унции","purity":"925 / 1000","quality":"пруф","diameterMm":"60,00 (±0,50)","thicknessMm":"7,00 (±0,50)","rectangular":false,"mintLogoUrl":"/image/Mints/mmd.webp"},"sameSeries":[{"id":"2537","title":"Переславль-Залесский","seriesName":"Золотое кольцо России","faceValue":"5 рублей","imageUrl":"/image/coins/5612-0005.webp","metalCode":"Au","metalColor":"#FFD700","metalCodes":["Au","Ag"],"metalName":"Серебро/золото","weightG":"23,30 / 16,20","rectangular":false},{"id":"2538","title":"Александров","seriesName":"Золотое кольцо России","faceValue":"5 рублей","imageUrl":"/image/coins/5612-0006.webp","metalCode":"Au","metalColor":"#FFD700","metalCodes":["Au","Ag"],"metalName":"Серебро/золото","weightG":"23,30 / 16,20","rectangular":false},{"id":"2540","title":"Александров","seriesName":"Золотое кольцо России","faceValue":"100 рублей","imageUrl":"/image/coins/5617-0006.webp","metalCode":"Au","metalColor":"#FFD700","metalCodes":["Au","Ag"],"metalName":"Серебро/золото","weightG":"124,40 / 84,60","rectangular":false},{"id":"3994","title":"Боголюбово","seriesName":"Золотое кольцо России","faceValue":"5 рублей","imageUrl":"/image/coins/5612-0003.webp","metalCode":"Au","metalColor":"#FFD700","metalCodes":["Au","Ag"],"metalName":"Золото- серебро","weightG":"23,30 / 19,20","rectangular":false},{"id":"3995","title":"Юрьев-Польский","seriesName":"Золотое кольцо России","faceValue":"5 рублей","imageUrl":"/image/coins/5612-0004.webp","metalCode":"Au","metalColor":"#FFD700","metalCodes":["Au","Ag"],"metalName":"Золото- серебро","weightG":"23,30 / 19,20","rectangular":false},{"id":"3996","title":"Боголюбово","seriesName":"Золотое кольцо России","faceValue":"100 рублей","imageUrl":"/image/coins/5617-0003.webp","metalCode":"Au","metalColor":"#FFD700","metalCodes":["Au","Ag"],"metalName":"Золото- серебро","weightG":"124,40 / 105,60","rectangular":false}]}