{"coin":{"id":"3741","title":"Евразийский экономический союз","imageUrl":"/image/coins/5217-0045.webp","imageUrls":["/image/coins/5217-0045.webp","/image/coins/5217-0045r.webp"],"inCollection":false,"mintName":"Санкт-Петербургский монетный двор","mintShort":"СПМД","mintCountry":"Россия","year":2015,"faceValue":"100 рублей","metal":"Золото","metalCode":"Au","metalColor":"#FFD700","metalCodes":["Au"],"mintage":500,"weightG":"15,55","weightOz":"1/2 унции","purity":"999 / 1000","quality":"пруф","diameterMm":"30,00 (±0,25)","thicknessMm":"1,70 (±0,20)","rectangular":false,"mintLogoUrl":"/image/Mints/spmd.webp"},"sameSeries":[]}