{"coin":{"id":"3777","title":"150-летие со дня рождения А.П. Чехова","seriesName":"150-летие со дня рождения А.П. Чехова","imageUrl":"/image/coins/5216-0071.webp","imageUrls":["/image/coins/5216-0071.webp","/image/coins/5216-0071r.webp"],"inCollection":false,"mintName":"Санкт-Петербургский монетный двор","mintShort":"СПМД","mintCountry":"Россия","year":2009,"faceValue":"50 рублей","metal":"Золото","metalCode":"Au","metalColor":"#FFD700","metalCodes":["Au"],"mintage":1500,"weightG":"7,78","weightOz":"1/4 унции","purity":"999 / 1000","quality":"пруф","diameterMm":"22,60 (±0,15)","thicknessMm":"1,60 (±0,20)","rectangular":false,"mintLogoUrl":"/image/Mints/spmd.webp"},"sameSeries":[{"id":"2748","title":"150-летие со дня рождения А.П. Чехова","seriesName":"150-летие со дня рождения А.П. Чехова","faceValue":"3 рубля","imageUrl":"/image/coins/5111-0191.webp","metalCode":"Ag","metalColor":"#C0C0C0","metalCodes":["Ag"],"metalName":"Серебро","weightG":"31,1","rectangular":false},{"id":"2749","title":"150-летие со дня рождения А.П. Чехова","seriesName":"150-летие со дня рождения А.П. Чехова","faceValue":"100 рублей","imageUrl":"/image/coins/5117-0044.webp","metalCode":"Ag","metalColor":"#C0C0C0","metalCodes":["Ag"],"metalName":"Серебро","weightG":"1000,0","rectangular":false},{"id":"3778","title":"150-летие со дня рождения А.П. Чехова","seriesName":"150-летие со дня рождения А.П. Чехова","faceValue":"200 рублей","imageUrl":"/image/coins/5219-0016.webp","metalCode":"Au","metalColor":"#FFD700","metalCodes":["Au"],"metalName":"Золото","weightG":"31,1","rectangular":false}]}