{"coin":{"id":"4367","title":"Australian Wedge-tailed Eagle 2021 1 Kilo Gold Incused Coin","seriesName":"Australian Wedge-tailed Eagle","imageUrl":"/image/coins/foreign/australian-wedge-tailed-eagle-2021-1-kilo-gold-incused-coin-rev.webp","imageUrls":["/image/coins/foreign/australian-wedge-tailed-eagle-2021-1-kilo-gold-incused-coin-obv.webp","/image/coins/foreign/australian-wedge-tailed-eagle-2021-1-kilo-gold-incused-coin-box.webp","/image/coins/foreign/australian-wedge-tailed-eagle-2021-1-kilo-gold-incused-coin-cert.webp"],"imageUrlRoles":["obverse","box","certificate"],"inCollection":false,"mintName":"The Perth Mint","mintShort":"Perth Mint","mintCountry":"Австралия","year":2021,"faceValue":"—","metal":"Золото","metalCode":"Au","metalColor":"#FFD700","metalCodes":["Au"],"mintage":250,"weightG":"1000","weightOz":"1 кг","purity":"9999/10000","quality":"Proof","diameterMm":"75.9","thicknessMm":"16","catalogSuffix":"25x41aaa","rectangular":false,"priceDisplay":"AUD 349.00"},"sameSeries":[{"id":"4750","title":"Australian Wedge-tailed Eagle 2025 1oz Silver Coloured Coin in Card","seriesName":"Australian Wedge-tailed Eagle","faceValue":"1 доллар","imageUrl":"/image/coins/foreign/australian-wedge-tailed-eagle-2025-1oz-silver-coloured-coin-in-card-rev.webp","metalCode":"Ag","metalColor":"#C0C0C0","metalCodes":["Ag"],"metalName":"Серебро","weightG":"31.1","rectangular":false},{"id":"4400","title":"Australian Wedge-tailed Eagle 2025 5oz Silver Reverse Proof Ultra High Relief Coin","seriesName":"Australian Wedge-tailed Eagle","faceValue":"8 долларов","imageUrl":"/image/coins/foreign/australian-wedge-tailed-eagle-2025-5oz-silver-reverse-proof-ultra-high-relief-coin-rev.webp","metalCode":"Ag","metalColor":"#C0C0C0","metalCodes":["Ag"],"metalName":"Серебро","weightG":"155.5","rectangular":false},{"id":"4399","title":"Australian Wedge-tailed Eagle 2025 5oz Gold Proof Ultra High Relief Gilded Coin","seriesName":"Australian Wedge-tailed Eagle","faceValue":"500 долларов","imageUrl":"/image/coins/foreign/australian-wedge-tailed-eagle-2025-5oz-gold-proof-ultra-high-relief-gilded-coin-rev.webp","metalCode":"Au","metalColor":"#FFD700","metalCodes":["Au"],"metalName":"Золото","weightG":"155.5","rectangular":false},{"id":"4398","title":"Australian Wedge-tailed Eagle 2025 2oz Silver Proof Ultra High Relief Gilded Coin","seriesName":"Australian Wedge-tailed Eagle","faceValue":"2 доллара","imageUrl":"/image/coins/foreign/australian-wedge-tailed-eagle-2025-2oz-silver-proof-ultra-high-relief-gilded-coin-rev.webp","metalCode":"Ag","metalColor":"#C0C0C0","metalCodes":["Ag"],"metalName":"Серебро","weightG":"62.2","rectangular":false},{"id":"4397","title":"Australian Wedge-tailed Eagle 2025 1oz Silver Reverse Proof Ultra High Relief Coin","seriesName":"Australian Wedge-tailed Eagle","faceValue":"1 доллар","imageUrl":"/image/coins/foreign/australian-wedge-tailed-eagle-2025-1oz-silver-reverse-proof-ultra-high-relief-coin-rev.webp","metalCode":"Ag","metalColor":"#C0C0C0","metalCodes":["Ag"],"metalName":"Серебро","weightG":"31.1","rectangular":false},{"id":"4395","title":"Australian Wedge-tailed Eagle 2025 1oz Gold Reverse Proof Ultra High Relief Coin","seriesName":"Australian Wedge-tailed Eagle","faceValue":"100 долларов","imageUrl":"/image/coins/foreign/australian-wedge-tailed-eagle-2025-1oz-gold-reverse-proof-ultra-high-relief-coin-rev.webp","metalCode":"Au","metalColor":"#FFD700","metalCodes":["Au"],"metalName":"Золото","weightG":"31.1","rectangular":false}]}