{"coin":{"id":"4467","title":"Fu Lu Shou 2023 5oz Silver Antiqued Coloured Coin","seriesName":"Fu Lu Shou","imageUrl":"/image/coins/foreign/fu-lu-shou-2023-5oz-silver-antiqued-coloured-coin-rev.webp","imageUrls":["/image/coins/foreign/fu-lu-shou-2023-5oz-silver-antiqued-coloured-coin-obv.webp","/image/coins/foreign/fu-lu-shou-2023-5oz-silver-antiqued-coloured-coin-box.webp","/image/coins/foreign/fu-lu-shou-2023-5oz-silver-antiqued-coloured-coin-cert.webp"],"imageUrlRoles":["obverse","box","certificate"],"inCollection":false,"mintName":"The Perth Mint","mintShort":"Perth Mint","mintCountry":"Тувалу","year":2023,"faceValue":"5 долларов","metal":"Серебро","metalCode":"Ag","metalColor":"#C0C0C0","metalCodes":["Ag"],"mintage":388,"weightG":"155.5","weightOz":"5 унций","weightOzDisplay":"5 унций","weightLabel":"5 унций · 155,5 г","purity":"9999/10000","quality":"Proof, Coloured","diameterMm":"55.9","thicknessMm":"7.5","catalogSuffix":"25u68zaa","rectangular":false,"priceDisplay":"AUD 204.99"},"sameSeries":[]}