{"coin":{"id":"4484","title":"Harry Potter™ and the Goblet of Fire 2025 2oz Silver Proof Coloured Coin","seriesName":"Harry Potter™","imageUrl":"/image/coins/foreign/harry-potter-goblet-of-fire-2025-2oz-silver-proof-coloured-coin-rev.webp","imageUrls":["/image/coins/foreign/harry-potter-goblet-of-fire-2025-2oz-silver-proof-coloured-coin-obv.webp","/image/coins/foreign/harry-potter-goblet-of-fire-2025-2oz-silver-proof-coloured-coin-box.webp","/image/coins/foreign/harry-potter-goblet-of-fire-2025-2oz-silver-proof-coloured-coin-cert.webp"],"imageUrlRoles":["obverse","box","certificate"],"inCollection":false,"mintName":"The Perth Mint","mintShort":"Perth Mint","mintCountry":"Ниуэ","year":2025,"faceValue":"3 доллара","metal":"Серебро","metalCode":"Ag","metalColor":"#C0C0C0","metalCodes":["Ag"],"mintage":1000,"weightG":"62.2","weightOz":"2","purity":"999/1000","quality":"Proof, Coloured","lengthMm":"60","widthMm":"40","catalogSuffix":"25y52baa","rectangular":true,"priceDisplay":"AUD 365.00"},"sameSeries":[{"id":"4488","title":"Harry Potter™ and the Sorcerer's Stone 2025 2oz Silver Proof Coloured Coin","seriesName":"Harry Potter™","faceValue":"3 доллара","imageUrl":"/image/coins/foreign/harry-potter-and-the-sorcerers-stone-2025-2oz-silver-proof-coloured-coin-rev.webp","metalCode":"Ag","metalColor":"#C0C0C0","metalCodes":["Ag"],"metalName":"Серебро","weightG":"62.2","rectangular":true},{"id":"4487","title":"Harry Potter™ and the Prisoner of Azkaban 2025 2oz Silver Proof Coloured Coin","seriesName":"Harry Potter™","faceValue":"3 доллара","imageUrl":"/image/coins/foreign/harry-potter-prisoner-of-azkaban-2025-2oz-silver-proof-coloured-coin-rev.webp","metalCode":"Ag","metalColor":"#C0C0C0","metalCodes":["Ag"],"metalName":"Серебро","weightG":"62.2","rectangular":true},{"id":"4486","title":"Harry Potter™ and the Order of the Phoenix 2025 2oz Silver Proof Coloured Coin","seriesName":"Harry Potter™","faceValue":"3 доллара","imageUrl":"/image/coins/foreign/harry-potter-and-the-order-of-the-phoenix-2025-2oz-silver-proof-coloured-coin-rev.webp","metalCode":"Ag","metalColor":"#C0C0C0","metalCodes":["Ag"],"metalName":"Серебро","weightG":"62.2","rectangular":true},{"id":"4485","title":"Harry Potter™ and the Half-Blood Prince 2025 2oz Silver Proof Coloured Coin","seriesName":"Harry Potter™","faceValue":"3 доллара","imageUrl":"/image/coins/foreign/harry-potter-and-the-half-blood-prince-2025-2oz-silver-proof-coloured-coin-rev.webp","metalCode":"Ag","metalColor":"#C0C0C0","metalCodes":["Ag"],"metalName":"Серебро","weightG":"62.2","rectangular":true},{"id":"4483","title":"Harry Potter™ and the Deathly Hallows 2025 2oz Silver Proof Coloured Coin","seriesName":"Harry Potter™","faceValue":"3 доллара","imageUrl":"/image/coins/foreign/harry-potter-and-the-deathly-hallows-2025-2oz-silver-proof-coloured-coin-rev.webp","metalCode":"Ag","metalColor":"#C0C0C0","metalCodes":["Ag"],"metalName":"Серебро","weightG":"62.2","rectangular":true},{"id":"4482","title":"Harry Potter™ and the Chamber of Secrets 2025 2oz Silver Proof Coloured Coin","seriesName":"Harry Potter™","faceValue":"3 доллара","imageUrl":"/image/coins/foreign/harry-potter-chamber-of-secrets-2025-2oz-silver-proof-coloured-coin-rev.webp","metalCode":"Ag","metalColor":"#C0C0C0","metalCodes":["Ag"],"metalName":"Серебро","weightG":"62.2","rectangular":true}]}