{"coin":{"id":"70","title":"80-летие национального исследовательского центра «Курчатовский институт» и 120-летие со дня рождения академиков И.В. Курчатова и А.П. Александрова","imageUrl":"https://www.cbr.ru/legacy/PhotoStore/img/5111-0484.jpg","imageUrls":["https://www.cbr.ru/legacy/PhotoStore/img/5111-0484.jpg","https://www.cbr.ru/legacy/PhotoStore/img/5111-0484r.jpg"],"inCollection":false,"mintName":"—","mintCountry":"Россия","year":2023,"faceValue":"3 рубля","metal":"серебро 925/1000","purity":"925/1000"},"sameSeries":[]}